pyftms/__init__.py
pyftms/__main__.py
pyftms/client/__init__.py
pyftms/client/client.py
pyftms/client/const.py
pyftms/client/errors.py
pyftms/client/manager.py
pyftms/client/backends/__init__.py
pyftms/client/backends/controller.py
pyftms/client/backends/event.py
pyftms/client/backends/updater.py
pyftms/client/machines/__init__.py
pyftms/client/machines/cross_trainer.py
pyftms/client/machines/indoor_bike.py
pyftms/client/machines/rower.py
pyftms/client/machines/treadmill.py
pyftms/client/properties/__init__.py
pyftms/client/properties/device_info.py
pyftms/client/properties/features.py
pyftms/client/properties/machine_type.py
pyftms/models/__init__.py
pyftms/models/common.py
pyftms/models/control_point.py
pyftms/models/machine_status.py
pyftms/models/spin_down.py
pyftms/models/training_status.py
pyftms/models/realtime_data/__init__.py
pyftms/models/realtime_data/common.py
pyftms/models/realtime_data/cross_trainer.py
pyftms/models/realtime_data/indoor_bike.py
pyftms/models/realtime_data/rower.py
pyftms/models/realtime_data/treadmill.py
pyftms/serializer/__init__.py
pyftms/serializer/list.py
pyftms/serializer/model.py
pyftms/serializer/num.py
pyftms/serializer/serializer.py
pyftms-0.4.15.dist-info/METADATA
pyftms-0.4.15.dist-info/WHEEL
pyftms-0.4.15.dist-info/licenses/LICENSE
pyftms-0.4.15.dist-info/RECORD
